hive/crypto/__init__.py
hive/crypto/__version__.py
hive/crypto/keygen.py
hive_crypto-0.0.1.dist-info/METADATA
hive_crypto-0.0.1.dist-info/WHEEL
hive_crypto-0.0.1.dist-info/entry_points.txt
hive_crypto-0.0.1.dist-info/top_level.txt
hive_crypto-0.0.1.dist-info/RECORD
